dfa_sampler/__init__.py
dfa_sampler/dfa_sampler.py
dfa_sampler-0.1.1.dist-info/LICENSE
dfa_sampler-0.1.1.dist-info/METADATA
dfa_sampler-0.1.1.dist-info/WHEEL
dfa_sampler-0.1.1.dist-info/RECORD
