Metadata-Version: 2.1
Name: dfa-sampler
Version: 0.1.1
Summary: Library for implementing dfa sampling strategies (pull requests welcome).
License: MIT
Author: Marcell Vazquez-Chanlatte
Author-email: mvc@linux.com
Requires-Python: >=3.10,<4.0
Classifier: License :: OSI Approved :: MIT License
Classifier: Programming Language :: Python :: 3
Classifier: Programming Language :: Python :: 3.10
Classifier: Programming Language :: Python :: 3.11
Classifier: Programming Language :: Python :: 3.12
Requires-Dist: dfa (>=4.6.4,<5.0.0)
Requires-Dist: dfa-mutate (>=0.1.3,<0.2.0)
